bamboolib/__init__.py
bamboolib/__main__.py
bamboolib/_authorization.py
bamboolib/_environment.py
bamboolib/_path.py
bamboolib/_server_api.py
bamboolib/_types.py
bamboolib/config.py
bamboolib/df_manager.py
bamboolib/grid.py
bamboolib/version.py
bamboolib/wrangler.py
bamboolib/assets/img/long_to_wide.png
bamboolib/assets/img/wide_to_long.png
bamboolib/datasets/.DS_Store
bamboolib/datasets/__init__.py
bamboolib/datasets/get_datasets.py
bamboolib/datasets/sales.csv
bamboolib/datasets/titanic.csv
bamboolib/datasets/__pycache__/__init__.cpython-37.pyc
bamboolib/datasets/__pycache__/__init__.cpython-38.pyc
bamboolib/datasets/__pycache__/__init__.cpython-39.pyc
bamboolib/datasets/__pycache__/get_datasets.cpython-37.pyc
bamboolib/datasets/__pycache__/get_datasets.cpython-38.pyc
bamboolib/datasets/__pycache__/get_datasets.cpython-39.pyc
bamboolib/edaviz/__init__.py
bamboolib/edaviz/__modules__.py
bamboolib/edaviz/base.py
bamboolib/edaviz/constants.py
bamboolib/edaviz/data_types.py
bamboolib/edaviz/interactive_histogram.py
bamboolib/edaviz/plots.py
bamboolib/edaviz/timeseries_plot.py
bamboolib/edaviz/utils.py
bamboolib/edaviz/z_legacy.py
bamboolib/helper/__init__.py
bamboolib/helper/error.py
bamboolib/helper/gui_outlets.py
bamboolib/helper/gui_viewables.py
bamboolib/helper/utils.py
bamboolib/loaders/__init__.py
bamboolib/loaders/databricks_database_table_loader.py
bamboolib/loaders/dummy_data.py
bamboolib/plugins/__init__.py
bamboolib/plugins/_adapters.py
bamboolib/plugins/_base_classes.py
bamboolib/plugins/_registry.py
bamboolib/plugins/_utils.py
bamboolib/setup/__init__.py
bamboolib/setup/_extensions.py
bamboolib/setup/file_logger.py
bamboolib/setup/import_.py
bamboolib/setup/ipython_display.py
bamboolib/setup/module_view.py
bamboolib/setup/user_symbols.py
bamboolib/static/extension.js
bamboolib/static/index.js
bamboolib/static/index.js.map
bamboolib/transformation_plugins/__init__.py
bamboolib/transformation_plugins/bulk_change_datatype.py
bamboolib-1.30.18.dist-info/LICENSE
bamboolib-1.30.18.dist-info/METADATA
bamboolib-1.30.18.dist-info/WHEEL
bamboolib-1.30.18.dist-info/top_level.txt
bamboolib-1.30.18.dist-info/RECORD
